asyncio_nutclient/__init__.py
asyncio_nutclient/nutclient.py
asyncio_nutclient/py.typed
asyncio_nutclient/version.py
asyncio_nutclient-0.0.5.dist-info/LICENSE
asyncio_nutclient-0.0.5.dist-info/METADATA
asyncio_nutclient-0.0.5.dist-info/WHEEL
asyncio_nutclient-0.0.5.dist-info/top_level.txt
asyncio_nutclient-0.0.5.dist-info/RECORD
