Metadata-Version: 2.1
Name: asyncio_nutclient
Version: 0.0.5
Summary: Library that talks Network UPS Tools Daemon in AsyncIO way.
Home-page: https://github.com/vincentto13/asyncio_nutclient
Author: Paweł Rapkiewicz
Author-email: pawel.rapkiewicz@gmail.com
License: MIT License
Platform: UNKNOWN
Classifier: Programming Language :: Python :: 3
Classifier: License :: OSI Approved :: MIT License
Classifier: Operating System :: OS Independent
License-File: LICENSE
